{
    "id":100025,
    "name":"Arachas Behemoth",
    "img":"arachasBehemoth.png",
    "fight":6,
    "type":3,
    "position":"middle",
    "loyalty":true,
    "timer":0,
    "prepare":
    {
        "int":[["geneNum",1],["damage",1],["pro",2],["id",100024]]
    },
    "DeployEffect":
    {
        "steps":
        {
            "function":
            [
                {
                    "name":"addProtectionByN",
                    "parameter":["self","pro"]
                }
            ]
        }
    },
    "DeployPassiveEffect":
    {
        "condition":
        {
            "signal":
            {
                "name":"eatTarget"
            }
        },
        "steps":
        {
            "function":
            [
                {
                    "name":"generatorNCard",
                    "parameter":["id","selfRow","self","geneNum","this"]
                },
                {
                    "name":"damageByNUnseenProtection",
                    "parameter":["self","damage"]
                }
            ]
        }
    }
}